LICENSE.txt
MANIFEST.in
README.rst
requirements.txt
setup.cfg
setup.py
test_requirements.txt
revolut/__init__.py
revolut/base.py
revolut/business.py
revolut/exceptions.py
revolut/merchant.py
revolut/session.py
revolut/utils.py
revolut_python.egg-info/PKG-INFO
revolut_python.egg-info/SOURCES.txt
revolut_python.egg-info/dependency_links.txt
revolut_python.egg-info/requires.txt
revolut_python.egg-info/top_level.txt
tools/revolut_genkey.sh
tools/revolut_getjwt.py
tools/revolut_gettokens.py