Metadata-Version: 2.1
Name: revolut-python
Version: 0.9.1
Summary: Revolut API client for Python
Home-page: https://github.com/emesik/revolut-python/
Author: Michał Sałaban
Author-email: michal@salaban.info
License: BSD-3-Clause
Keywords: revolut payments
Platform: UNKNOWN
Classifier: Development Status :: 4 - Beta
Classifier: Intended Audience :: Developers
Classifier: License :: OSI Approved :: BSD License
Classifier: Operating System :: OS Independent
Classifier: Programming Language :: Python
Classifier: Programming Language :: Python :: 2.7
Classifier: Programming Language :: Python :: 3.6
Classifier: Programming Language :: Python :: 3.7
License-File: LICENSE.txt
